Workbook

Sheet Base_Data
A1: Day | B1: Customers | C1: Avg_Bill | D1: Revenue | E1: Staff_Count | F1: Staff_Cost | G1: Customer_Rating
A2: 1 | B2: 117 | C2: 422 | D2: =B2*C2 | E2: 5 | F2: 2500 | G2: 3.8
A3: 2 | B3: 102 | C3: 445 | D3: =B3*C3 | E3: 6 | F3: 3000 | G3: 4.6
A4: 3 | B4: 114 | C4: 455 | D4: =B4*C4 | E4: 6 | F4: 3000 | G4: 3.6
A5: 4 | B5: 109 | C5: 451 | D5: =B5*C5 | E5: 6 | F5: 3000 | G5: 4.4
A6: 5 | B6: 113 | C6: 464 | D6: =B6*C6 | E6: 6 | F6: 3000 | G6: 4
A7: 6 | B7: 125 | C7: 434 | D7: =B7*C7 | E7: 5 | F7: 2500 | G7: 3.9
A8: 7 | B8: 142 | C8: 463 | D8: =B8*C8 | E8: 5 | F8: 2500 | G8: 3.5
A9: 8 | B9: 134 | C9: 450 | D9: =B9*C9 | E9: 6 | F9: 3000 | G9: 4.4
A10: 9 | B10: 127 | C10: 441 | D10: =B10*C10 | E10: 6 | F10: 3000 | G10: 4.4
A11: 10 | B11: 118 | C11: 426 | D11: =B11*C11 | E11: 6 | F11: 3000 | G11: 3.9
A12: 11 | B12: 109 | C12: 402 | D12: =B12*C12 | E12: 7 | F12: 3500 | G12: 3.5
A13: 12 | B13: 100 | C13: 419 | D13: =B13*C13 | E13: 8 | F13: 4000 | G13: 3.6
... A181: 180 | B181: 325 | C181: 480 | D181: =B181*C181 | E181: 4 | F181: 2000 | G181: 4.1

Sheet Price_Increase
A1: Day | B1: Old_Customers | C1: Old_Bill | D1: New_Bill | E1: Expected_Customers | F1: New_Revenue
A2: =Base_Data!A2 | B2: =Base_Data!B2 | C2: =Base_Data!C2 | D2: =C2*1.10 | E2: =B2*0.90 | F2: =D2*E2
A3: =Base_Data!A3 | B3: =Base_Data!B3 | C3: =Base_Data!C3 | D3: =C3*1.10 | E3: =B3*0.90 | F3: =D3*E3
A4: =Base_Data!A4 | B4: =Base_Data!B4 | C4: =Base_Data!C4 | D4: =C4*1.10 | E4: =B4*0.90 | F4: =D4*E4
A5: =Base_Data!A5 | B5: =Base_Data!B5 | C5: =Base_Data!C5 | D5: =C5*1.10 | E5: =B5*0.90 | F5: =D5*E5
A6: =Base_Data!A6 | B6: =Base_Data!B6 | C6: =Base_Data!C6 | D6: =C6*1.10 | E6: =B6*0.90 | F6: =D6*E6
A7: =Base_Data!A7 | B7: =Base_Data!B7 | C7: =Base_Data!C7 | D7: =C7*1.10 | E7: =B7*0.90 | F7: =D7*E7
A8: =Base_Data!A8 | B8: =Base_Data!B8 | C8: =Base_Data!C8 | D8: =C8*1.10 | E8: =B8*0.90 | F8: =D8*E8
A9: =Base_Data!A9 | B9: =Base_Data!B9 | C9: =Base_Data!C9 | D9: =C9*1.10 | E9: =B9*0.90 | F9: =D9*E9
A10: =Base_Data!A10 | B10: =Base_Data!B10 | C10: =Base_Data!C10 | D10: =C10*1.10 | E10: =B10*0.90 | F10: =D10*E10
A11: =Base_Data!A11 | B11: =Base_Data!B11 | C11: =Base_Data!C11 | D11: =C11*1.10 | E11: =B11*0.90 | F11: =D11*E11
A12: =Base_Data!A12 | B12: =Base_Data!B12 | C12: =Base_Data!C12 | D12: =C12*1.10 | E12: =B12*0.90 | F12: =D12*E12
A13: =Base_Data!A13 | B13: =Base_Data!B13 | C13: =Base_Data!C13 | D13: =C13*1.10 | E13: =B13*0.90 | F13: =D13*E13
... A181: =Base_Data!A181 | B181: =Base_Data!B181 | C181: =Base_Data!C181 | D181: =C181*1.10 | E181: =B181*0.90 | F181: =D181*E181

Sheet Discount_Scenario
A1: Day | B1: Old_Customers | C1: Old_Bill | D1: New_Bill | E1: Expected_Customers | F1: New_Revenue
A2: =Base_Data!A2 | B2: =Base_Data!B2 | C2: =Base_Data!C2 | D2: =C2*0.85 | E2: =B2*1.20 | F2: =D2*E2
A3: =Base_Data!A3 | B3: =Base_Data!B3 | C3: =Base_Data!C3 | D3: =C3*0.85 | E3: =B3*1.20 | F3: =D3*E3
A4: =Base_Data!A4 | B4: =Base_Data!B4 | C4: =Base_Data!C4 | D4: =C4*0.85 | E4: =B4*1.20 | F4: =D4*E4
A5: =Base_Data!A5 | B5: =Base_Data!B5 | C5: =Base_Data!C5 | D5: =C5*0.85 | E5: =B5*1.20 | F5: =D5*E5
A6: =Base_Data!A6 | B6: =Base_Data!B6 | C6: =Base_Data!C6 | D6: =C6*0.85 | E6: =B6*1.20 | F6: =D6*E6
A7: =Base_Data!A7 | B7: =Base_Data!B7 | C7: =Base_Data!C7 | D7: =C7*0.85 | E7: =B7*1.20 | F7: =D7*E7
A8: =Base_Data!A8 | B8: =Base_Data!B8 | C8: =Base_Data!C8 | D8: =C8*0.85 | E8: =B8*1.20 | F8: =D8*E8
A9: =Base_Data!A9 | B9: =Base_Data!B9 | C9: =Base_Data!C9 | D9: =C9*0.85 | E9: =B9*1.20 | F9: =D9*E9
A10: =Base_Data!A10 | B10: =Base_Data!B10 | C10: =Base_Data!C10 | D10: =C10*0.85 | E10: =B10*1.20 | F10: =D10*E10
A11: =Base_Data!A11 | B11: =Base_Data!B11 | C11: =Base_Data!C11 | D11: =C11*0.85 | E11: =B11*1.20 | F11: =D11*E11
A12: =Base_Data!A12 | B12: =Base_Data!B12 | C12: =Base_Data!C12 | D12: =C12*0.85 | E12: =B12*1.20 | F12: =D12*E12
A13: =Base_Data!A13 | B13: =Base_Data!B13 | C13: =Base_Data!C13 | D13: =C13*0.85 | E13: =B13*1.20 | F13: =D13*E13
... A181: =Base_Data!A181 | B181: =Base_Data!B181 | C181: =Base_Data!C181 | D181: =C181*0.85 | E181: =B181*1.20 | F181: =D181*E181

Sheet Increase_Staff
A1: Day | B1: Old_Staff | C1: New_Staff | D1: Old_Customers | E1: New_Customers | F1: Old_Rating | G1: New_Rating | H1: Old_Cost | I1: New_Cost
A2: =Base_Data!A2 | B2: =Base_Data!E2 | C2: =B2+2 | D2: =Base_Data!B2 | E2: =D2*1.20 | F2: =Base_Data!G2 | G2: =F2+0.3 | H2: =Base_Data!F2 | I2: =H2+1000
A3: =Base_Data!A3 | B3: =Base_Data!E3 | C3: =B3+2 | D3: =Base_Data!B3 | E3: =D3*1.20 | F3: =Base_Data!G3 | G3: =F3+0.3 | H3: =Base_Data!F3 | I3: =H3+1000
A4: =Base_Data!A4 | B4: =Base_Data!E4 | C4: =B4+2 | D4: =Base_Data!B4 | E4: =D4*1.20 | F4: =Base_Data!G4 | G4: =F4+0.3 | H4: =Base_Data!F4 | I4: =H4+1000
A5: =Base_Data!A5 | B5: =Base_Data!E5 | C5: =B5+2 | D5: =Base_Data!B5 | E5: =D5*1.20 | F5: =Base_Data!G5 | G5: =F5+0.3 | H5: =Base_Data!F5 | I5: =H5+1000
A6: =Base_Data!A6 | B6: =Base_Data!E6 | C6: =B6+2 | D6: =Base_Data!B6 | E6: =D6*1.20 | F6: =Base_Data!G6 | G6: =F6+0.3 | H6: =Base_Data!F6 | I6: =H6+1000
A7: =Base_Data!A7 | B7: =Base_Data!E7 | C7: =B7+2 | D7: =Base_Data!B7 | E7: =D7*1.20 | F7: =Base_Data!G7 | G7: =F7+0.3 | H7: =Base_Data!F7 | I7: =H7+1000
A8: =Base_Data!A8 | B8: =Base_Data!E8 | C8: =B8+2 | D8: =Base_Data!B8 | E8: =D8*1.20 | F8: =Base_Data!G8 | G8: =F8+0.3 | H8: =Base_Data!F8 | I8: =H8+1000
A9: =Base_Data!A9 | B9: =Base_Data!E9 | C9: =B9+2 | D9: =Base_Data!B9 | E9: =D9*1.20 | F9: =Base_Data!G9 | G9: =F9+0.3 | H9: =Base_Data!F9 | I9: =H9+1000
A10: =Base_Data!A10 | B10: =Base_Data!E10 | C10: =B10+2 | D10: =Base_Data!B10 | E10: =D10*1.20 | F10: =Base_Data!G10 | G10: =F10+0.3 | H10: =Base_Data!F10 | I10: =H10+1000
A11: =Base_Data!A11 | B11: =Base_Data!E11 | C11: =B11+2 | D11: =Base_Data!B11 | E11: =D11*1.20 | F11: =Base_Data!G11 | G11: =F11+0.3 | H11: =Base_Data!F11 | I11: =H11+1000
A12: =Base_Data!A12 | B12: =Base_Data!E12 | C12: =B12+2 | D12: =Base_Data!B12 | E12: =D12*1.20 | F12: =Base_Data!G12 | G12: =F12+0.3 | H12: =Base_Data!F12 | I12: =H12+1000
A13: =Base_Data!A13 | B13: =Base_Data!E13 | C13: =B13+2 | D13: =Base_Data!B13 | E13: =D13*1.20 | F13: =Base_Data!G13 | G13: =F13+0.3 | H13: =Base_Data!F13 | I13: =H13+1000
... A181: =Base_Data!A181 | B181: =Base_Data!E181 | C181: =B181+2 | D181: =Base_Data!B181 | E181: =D181*1.20 | F181: =Base_Data!G181 | G181: =F181+0.3 | H181: =Base_Data!F181 | I181: =H181+1000

Sheet Decision_Comparison
A1: Decision | B1: Revenue_Impact | C1: Cost_Impact | D1: Customer_Experience
A2: Increase Price | B2: High | C2: Neutral | D2: Negative
A3: Discount | B3: Neutral | C3: Negative | D3: Positive
A4: Increase Staff | B4: Positive | C4: High | D4: Very Positive
A5: Reduce Staff | B5: Negative | C5: Low | D5: Negative
